app/__init__.py
app/data/raw/matches/matches.csv
app/data/raw/players/keepers.csv
app/data/raw/players/players.csv
app/data/raw/rankings/england/2017-2018/rankings_premier_league_2017-2018.csv
app/data/raw/rankings/france/2017-2018/rankings_ligue_1_2017-2018.csv
app/data/raw/rankings/germany/2017-2018/rankings_bundesliga_2017-2018.csv
app/data/raw/rankings/italy/2017-2018/rankings_serie_a_2017-2018.csv
app/data/raw/rankings/spain/2017-2018/rankings_liga_2017-2018.csv
app/data/raw/teams/teams.csv
app/feature_engineering/__init__.py
app/feature_engineering/feature_engineering.py
app/feature_engineering/team_notes_fixtures.py
app/feature_engineering/temporal_features.py
app/main.py
app/mlflow/tracking.py
app/model/1_RandomForestClassifier.ipynb
app/model/2_SGDClassifier.ipynb
app/model/3_XGBoostClassifier.ipynb
app/model/4_CatBoostClassifier_weekly.ipynb
app/model_testing/4_CatBoostClassifier_weekly.ipynb
app/predicting/__init__.py
app/predicting/predicting.py
app/processing/ranking/__init__.py
app/processing/ranking/league_ranking.py
app/processing/ranking/situation_ranking.py
app/processing/teams/__init__.py
app/processing/teams/teams.py
app/routers/healthz.py
app/routers/hello_world.py
app/scrapers/__init__.py
app/scrapers/fotmob_scraper.py
app/scrapers/meteo_scraper.py
app/scrapers/odds_scraper.py
app/scrapers/odds_scraper_1.py
app/scrapers/rubiscore_rounds_dates.ipynb
app/scrapers/sofascore_scraper.py
app/scrapers/transfers_scraper.py
app/updating/__init__.py
app/updating/update_dataset.py
app/utils/__init__.py
app/utils/config.py
app/utils/date.py
app/utils/document_notebook.py
app/utils/format.py
api_python_bet_project-0.1.39.dist-info/METADATA
api_python_bet_project-0.1.39.dist-info/WHEEL
api_python_bet_project-0.1.39.dist-info/RECORD
