Metadata-Version: 2.1
Name: api-python-bet-project
Version: 0.1.39
Summary: API-python-bet-project
Author: Julio Martinez del Pino
Author-email: juliomdp92@gmail.com
Requires-Python: >=3.10,<3.13
Classifier: Programming Language :: Python :: 3
Classifier: Programming Language :: Python :: 3.10
Classifier: Programming Language :: Python :: 3.11
Classifier: Programming Language :: Python :: 3.12
Requires-Dist: beautifulsoup4 (==4.*)
Requires-Dist: catboost (==1.2.*)
Requires-Dist: fastapi[all] (==0.111.*)
Requires-Dist: imbalanced-learn (==0.13.*)
Requires-Dist: ipykernel (==6.*)
Requires-Dist: jupyter (==1.1.*)
Requires-Dist: lightgbm (==4.6.*)
Requires-Dist: markdown (==3.*)
Requires-Dist: matplotlib (==3.10.*)
Requires-Dist: mlflow (==2.22.*)
Requires-Dist: nbformat (==5.10.*)
Requires-Dist: numpy (==1.26.*)
Requires-Dist: openai (==1.*)
Requires-Dist: optuna (==4.4.*)
Requires-Dist: pandas (==2.*)
Requires-Dist: pyautogui (==0.9.*)
Requires-Dist: python-decouple (==3.*)
Requires-Dist: python-dotenv (==1.2.*)
Requires-Dist: requests (==2.32.*)
Requires-Dist: scikit-learn (==1.6.*)
Requires-Dist: selenium (==4.*)
Requires-Dist: selenium-scraper (==0.0.*)
Requires-Dist: smote (==0.*)
Requires-Dist: tqdm (==4.*)
Requires-Dist: undetected-chromedriver (==3.5.*)
Requires-Dist: unidecode (==1.3.*)
Requires-Dist: uvicorn (==0.29.*)
Requires-Dist: xgboost (==3.0.*)
